{"product":{"product_id":"52457338","country_of_origin_code":"US","environmental_segmentation":{"is_hazardous_material":false,"is_ingestible":false},"launch_date_time":"2017-04-30T07:00:00Z","music_movie_book_video_content":{},"dpci":"249-23-2766","item_kind":"Sellable","display_option":{},"parent_items":[{"parent_id":"52503274"}],"product_description":{"title":"Weston Welted Daybed -Queen - Halfmoon Black White - Cloth & Co.","downstream_description":"Perfect floating at the center of a room or flush against a wall, the simply cozy Weston Welted Daybed from Cloth & Co. provides a generously cushioned spot for your daily dose of relaxation. With clean lines, tailored upholstery and sleek tapered legs, this handcrafted piece is a classic of comfort that's so easy to coordinate.<br><br>Cloth & Company is where textile, technology and a tradition of craftmanship meet. Inspired by the latest trends in fashion that are brought to life using state-of-the-art digital printing and 3D technology. The end result is beautifully designed, made to order furniture.","bullet_description":"<B>Dimensions (Overall):</B> 24 inches (H) x 52.0 inches (W) x 74.0 inches (D)|<B>Care & Cleaning:</B> Spot or wipe clean|<B>Size:</B> Queen|<B>Material:</B> Espresso Pine, Metal (Frame)|<B>Surface Material:</B> Linen|<B>Weight:</B> 60 pounds|<B>Textile Material:</B> 55% Linen, 45% Cotton|<B>Pattern:</B> Printed pattern|<B>Upholstery:</B> Upholstered|<B>Assembly Details:</B> No assembly required|<B>Box spring required:</B> No|<B>Material: Fill 1:</B> Polyurethane Foam|<B>Material: Fill 2:</B> Polyester Fiber|<B>Warranty:</B> 1 year limited warranty. To obtain a copy of the manufacturer's or supplier's warranty for this item prior to purchasing the item, please call Target Guest Services at 1-800-591-3869","short_description":"ADULT BED ADULT BED 30 X 63 X 18"},"product_classification":{"item_type":{"category_type":"Item Type: Furniture","name":"beds","type":239710},"merchandise_type":"106430","merchandise_type_name":"beds and mattresses","product_type":596,"product_type_name":"FURNITURE","product_subtype":608,"product_subtype_name":"bedroom furniture"},"enrichment":{"buy_url":"https://www.target.com/p/weston-welted-daybed-queen-halfmoon-black-white-cloth-co/-/A-52457338","images":{"swatch_image":"GUEST_7b4f5702-58c2-4197-9d60-28841fbba749","base_url":"//target.scene7.com/is/image/Target/","primary_image":"GUEST_df1d6567-18d4-413b-a641-2bddbd03d69d","alternate_images":["GUEST_757462d5-dc6c-42f4-b3f6-68be9128595e","GUEST_ef1faec6-00c6-4a39-a49a-ab3fc2db8ace","GUEST_d23d546e-01e5-4af0-93fd-3de5958e88f1","GUEST_58beb63b-f818-45b4-8f39-31aae3547087"]},"sales_classification_nodes":[{"node_id":"4ym22"},{"node_id":"tp9m7"},{"node_id":"ms2w8"}],"return_policies":[{"day_count":120,"end_date":"9999-12-31","end_time":"00:00:00","id":16,"start_date":"2017-04-29","start_time":"00:00:00","type":"permanent","user_type":"best_guest"},{"day_count":90,"end_date":"9999-12-31","end_time":"00:00:00","id":16,"start_date":"2017-04-29","start_time":"00:00:00","type":"permanent","user_type":"regular_guest"}]},"product_brand":{"manufacturer_brand":"Cloth & Co.","brand":"Cloth & Co."},"package_dimensions":{"weight":62.0,"weight_unit_of_measure":"POUND","depth":30.0,"height":18.0,"width":63.0,"dimension_unit_of_measure":"INCH"},"variation":{"theme":"color & size","size":"Queen","color":"Black/Cream Print"},"relationship_type_code":"VC","merchandise_classification":{"class_id":23,"department_id":249,"class_name":"BEDS/HEADBOARDS","department_name":"FURNITURE","division_name":"DECORATIVE HOME","group_name":"HOME","sub_group_name":"DECORATIVE HOME"},"estore_item_status_code":"A","tax_category":{"tax_code_id":99999,"tax_code":"99999"},"merchandise_type_attributes":[{"values":[{"id":"241472","name":"Cotton"}],"id":"108688","name":"Material: Textile 2"},{"values":[{"id":"239365","name":"Espresso"}],"id":"108485","name":"Finish: Wood"},{"values":[{"id":"479218","name":"Online-Unique"}],"id":"161554","name":"Assortment Type"},{"values":[{"id":"240459","name":"Pine"},{"id":"240457","name":"Metal"}],"id":"108580","name":"Material: Frame"},{"values":[{"id":"530212","name":"Linen"}],"id":"108582","name":"Material: Surface"},{"values":[{"id":"421548","name":"no assembly required"}],"id":"140950","name":"Assembly details"},{"values":[{"id":"233576","name":"1 year limited warranty"}],"id":"107946","name":"Warranty Description"},{"values":[{"id":"826964","name":"spot or wipe clean"}],"id":"107703","name":"Care and Cleaning"},{"values":[{"id":"21334020","name":"no"}],"id":"303890","name":"box spring required"},{"values":[{"name":"52.000","unit_of_measure":"inches"}],"id":"107900","name":"Product Width"},{"values":[{"id":"230338","name":"Black"}],"id":"107707","name":"Product Color"},{"values":[{"name":"60","unit_of_measure":"pounds"}],"id":"107883","name":"Product Weight"},{"values":[{"id":"248307","name":"Linen"}],"id":"108578","name":"Material: Textile 1"},{"values":[{"name":"24","unit_of_measure":"inches"}],"id":"107882","name":"Product Height"},{"values":[{"id":"240439","name":"Polyurethane Foam"}],"id":"108579","name":"Material: Fill 1"},{"values":[{"name":"74.000","unit_of_measure":"inches"}],"id":"107881","name":"Product Depth"},{"values":[{"id":"239710","name":"beds"}],"id":"108496","name":"Item Type: Furniture"},{"values":[{"id":"240522","name":"upholstered"}],"id":"108596","name":"upholstery"},{"values":[{"id":"239775","name":"daybeds"}],"id":"108497","name":"furniture subtype"},{"values":[{"id":"232377","name":"Adult (18 years and up)"}],"id":"107886","name":"Targeted Audience"},{"values":[{"id":"242323","name":"Polyester Fiber"}],"id":"108690","name":"Material: Fill 2"},{"values":[{"name":"55"}],"id":"108692","name":"Material: Textile Percentage 1"},{"values":[{"name":"45"}],"id":"108693","name":"Material: Textile Percentage 2"},{"values":[{"id":"463506","name":"Repeating"}],"id":"157450","name":"pattern characteristics"},{"values":[{"id":"463510","name":"printed pattern"}],"id":"157451","name":"pattern application"},{"values":[{"id":"184357","name":"Queen"}],"id":"104725","name":"ABN Size"}],"identifiers":[{"barcode_type":"UPC","barcode_number":"191360087302","is_primary_barcode":true,"is_primary_vendor":true,"location_id":3991,"vendor_id":1331134},{"barcode_type":"UPC","barcode_number":"191360087302","is_primary_barcode":true,"is_primary_vendor":false,"location_id":3991,"vendor_id":1119877}],"is_parent_item":false,"product_vendors":[{"id":"1331134","is_primary_vendor":true,"location_id":3991,"manufacturer_style":"8706HLBLWH","vendor_name":"SKYLINE FURN MFG INC"},{"id":"1119877","is_primary_vendor":false,"location_id":3991,"manufacturer_style":"8706HLBLWH","vendor_name":"SKYLINE FURNITURE MFG INC"}],"return_method":"Mail In or Store","country_of_origin_name":"United States","estore_item_status":"Active","intended_launch_date_time":"2017-04-30T07:00:00Z","item_state":"READY_FOR_LAUNCH","net_content_quantity":{"unit_of_measure":"EACH","value":"1.0000"},"is_key_item":false,"assigned_selling_channels":["Sold Online"],"compliance":{"is_proposition_65":false},"price":{"list_price":{"price":1041.99,"max_price":0.0,"min_price":0.0},"offer_price":{"price":1041.99,"max_price":0.0,"min_price":0.0,"save_dollar":"0","save_percent":"0","price_type":"Reg"},"map_price":0.0},"shipping_handling":{"is_back_order_eligible":false,"receiving_facility_type":"ShipAlone","back_order_type":"Dropship (standard)","buy_unit_of_measure":"Each","handling_item_charge":{"item_bulky":false},"shipping_item_charge":{"per_order_charges":{"apo_fpo_express_one_day":80.0,"apo_fpo_seasonal":5.99,"apo_fpo_standard":5.99,"continental_express_one_day":80.0,"continental_seasonal":5.99,"continental_standard":5.99,"hawaii_express_one_day":80.0,"hawaii_seasonal":5.99,"hawaii_standard":5.99,"protectorates_express_one_day":80.0,"protectorates_seasonal":5.99,"protectorates_standard":5.99,"super_beyond_zips_seasonal":5.99,"super_beyond_zips_express_one_day":80.0,"super_beyond_zips_standard":5.99},"weight":62.0}},"availability":{"availability_status":"IN_STOCK"},"ratings_review":{"average_overall_rating":0.0,"total_review_count":0},"fulfilment":{"purchase_limit":99,"shipping_restriction":"false","shipping_exclusions":[{"code":"US-AK","description":"Alaska"},{"code":"US-HI","description":"Hawaii"},{"code":"US-PR","description":"Puerto Rico (see also separate entry under PR)"},{"code":"US-GU","description":"Guam (see also separate entry under GU)"},{"code":"US-AS","description":"American Samoa (see also separate entry under AS)"},{"code":"US-MP","description":"Northern Mariana Islands"},{"code":"US-UM","description":"United States Minor Outlying Islands"},{"code":"US-VI","description":"Virgin Islands, U.S."},{"code":"US-APO/FPO","description":"APO/FPO"}],"is_po_box_prohibited":true,"is_gift_wrap_eligible":"false","is_signature_required":"false","shipping_carrier":"UPS","is_hold":false,"is_rush":false,"is_ship_to_guest":false,"is_ship_to_store":false},"taxanomy":"{\"nodeId\":\"4ym22\",\"seoData\":{\"seo_h1\":\"Beds\",\"seo_title\":\"Beds : Target\",\"seo_keywords\":\"Beds, Bedroom Furniture, Furniture\",\"seo_description\":\"Shop Target for Beds you will love at great low prices. Spend $35+ or use your REDcard \\u0026 get free 2-day shipping on most items or same-day pick-up in store.\",\"canonical_url\":\"/c/beds-bedroom-furniture/-/N-4ym22\",\"image_path\":\"https://target.scene7.com/is/image/Target/51794027\",\"page_id\":\"/c/4ym22\",\"page_type\":\"category\",\"internal_index\":\"internalindex\",\"robots\":\"index, follow\"},\"children\":[],\"type\":\"Category\",\"priority\":800,\"breadcrumbs\":[\"Homepage\",\"Furniture\",\"Bedroom Furniture\",\"Beds\"]}"}}